clisy/__init__.py
clisy/skeleton.py
clisy/searcher/__init__.py
clisy/searcher/base_searcher.py
clisy/searcher/clisyfactory.py
clisy/searcher/searchoptions.py
clisy/searcher/searcher_impl/__init__.py
clisy/searcher/searcher_impl/amazon_searcher.py
clisy/searcher/searcher_impl/creative_commons_image_searcher.py
clisy/searcher/searcher_impl/duck_duck_go_searcher.py
clisy/searcher/searcher_impl/google_searcher.py
clisy/searcher/searcher_impl/imdb_searcher.py
clisy/searcher/searcher_impl/swiggy_searcher.py
clisy/searcher/searcher_impl/wikipedia_searcher.py
clisy/searcher/searcher_impl/wirecutter_searcher.py
clisy/webview/__init__.py
clisy/webview/web_browser_opener.py
clisy-0.0.4.dist-info/AUTHORS.rst
clisy-0.0.4.dist-info/LICENSE.txt
clisy-0.0.4.dist-info/METADATA
clisy-0.0.4.dist-info/WHEEL
clisy-0.0.4.dist-info/entry_points.txt
clisy-0.0.4.dist-info/top_level.txt
clisy-0.0.4.dist-info/RECORD
