Metadata-Version: 2.1
Name: clisy
Version: 0.0.4
Summary: A command line utility to search from command line using various search options and then open browser to see the results.
Home-page: https://github.com/nilukush/clisy/
Author: Nilesh Kumar
Author-email: nilukush@gmail.com
License: MIT
Project-URL: Documentation, https://pyscaffold.org/
Platform: any
Classifier: Development Status :: 4 - Beta
Classifier: Programming Language :: Python
License-File: LICENSE.txt
License-File: AUTHORS.rst
Requires-Dist: importlib-metadata ; python_version < "3.8"
Provides-Extra: testing
Requires-Dist: setuptools ; extra == 'testing'
Requires-Dist: pytest ; extra == 'testing'
Requires-Dist: pytest-cov ; extra == 'testing'
